[
	{ "name": "Kitavi Joseph", "job": "Software Engineer, Andela", "twitter": "sirjmkitavi", "pic": "https://droidcon.co.ke/img/Speakers/Kitavi__Joseph.jpg" },
	{ "name": "Otieno Rowland", "job": "Android Hoax Slayer", "twitter": "rowlandoti", "pic": "https://droidcon.co.ke/img/Speakers/Otieno_Rowland.jpg" },
	{ "name": "Roina Ochieng", "job": "Developer Relations Associate, Africa's Talking", "twitter": "roinochieng", "pic": "https://droidcon.co.ke/img/Speakers/Roina_Ochieng.jpg" },
	{ "name": "Nathan Mkaya", "job": "Novice:Order of the Green Droid", "twitter": "nathanmkaya", "pic": "https://droidcon.co.ke/img/Speakers/Nathan_Mkaya.jpg" },
	{ "name": "Kevin Mulugu", "job": "Software developer, Homepesa Sacco", "twitter": "kevvoh_", "pic": "https://droidcon.co.ke/img/Speakers/Kevin_Mulugu.png" },
	{ "name": "Charles Muchene", "job": "SenseiDev", "twitter": "charlesmuchene", "pic": "https://droidcon.co.ke/img/Speakers/Charles_Muchene.JPG" },
	{ "name": "Felicity Mecha", "job": "Community lead: AI Saturdays", "twitter": "fliquestarr", "pic": "https://droidcon.co.ke/img/Speakers/Felicity_Mecha.jpg" },
	{ "name": "Juma Allan", "job": "Android Engineer, Twiga Foods", "twitter": "_jumaallan", "pic": "https://droidcon.co.ke/img/Speakers/Juma_Allan.JPG" },
	{ "name": "Remy Mumoh", "job": "", "twitter": "", "pic": "https://droidcon.co.ke/img/Speakers/Remy_Mumoh.jpg" },
	{ "name": "Emmanuel Mutua", "job": "Android Developer", "twitter": "manuh_254", "pic": "https://droidcon.co.ke/img/Speakers/Emmanuel_Mutua.jpg" },
	{ "name": "Judy Ngure", "job": "Applications security specialist", "twitter": "Judy_infosec", "pic": "https://droidcon.co.ke/img/Speakers/judy_Ngure.png" },
	{ "name": "Dennis Riungu", "job": "Google Developer Group Kenya, Country mentor", "twitter": "denpalrius", "pic": "https://droidcon.co.ke/img/Speakers/Dennis_Riungu.jpg" },
	{ "name": "Eton Otieno", "job": "Code Zilla", "twitter": "eton_otieno", "pic": "https://droidcon.co.ke/img/Speakers/Eton_Otieno.jpg" },
	{ "name": "Moyinoluwa Adeyemi", "job": "Android Developer, Offgrid Electric", "twitter": "moyheen", "pic": "https://droidcon.co.ke/img/Speakers/Moyinoluwa_Adeyemi.jpg" },
	{ "name": "Thomas Kioko", "job": "Mobile Application Developer", "twitter": "code_wizard", "pic": "https://droidcon.co.ke/img/Speakers/Thomas_Kioko.JPG" },
	{ "name": "Marvin Collins", "job": "Apps:Lab KE", "twitter": "marvin_hosea", "pic": "https://droidcon.co.ke/img/Speakers/Marvin_Collins.jpg" },
	{ "name": "Danny Preussler", "job": "Head of Mobile, sporttotal.tv", "twitter": "PreusslerBerlin", "pic": "https://droidcon.co.ke/img/Speakers/Danny_Preussler.jpg" },
	{ "name": "Eston Karumbi", "job": "Android Developer, Andela", "twitter": "doc2dev", "pic": "https://droidcon.co.ke/img/Speakers/Eston_Karumbi.jpg" },
	{ "name": "Roger Taracha", "job": "Lead Android Engineer, Andela Kenya", "twitter": "TheDancerCodes", "pic": "https://droidcon.co.ke/img/Speakers/Roger_Taracha.jpg" },
	{ "name": "Valentine Rutto", "job": "Android developer, Sendy", "twitter": "ValentineRutto", "pic": "https://droidcon.co.ke/img/Speakers/Valentine_Rutto.jpg" },
	{ "name": "Mayowa Adegeye", "job": "Member of Technical Staff at Careem Networks GmbH", "twitter": "mayojava", "pic": "https://droidcon.co.ke/img/Speakers/Mayowa_Adegeye.jpg" },
	{ "name": "Temidayo Adefioye", "job": "geekofthrones", "twitter": "temidjoy", "pic": "https://droidcon.co.ke/img/Speakers/Temidayo_Adefioye.jpg" },
	{ "name": "Clare Mburu", "job": "CTO, BabyPie", "twitter": "mburuclare", "pic": "https://droidcon.co.ke/img/Speakers/Clare_Mburu.jpg" },
	{ "name": "Stephen Ebichondo", "job": "Expert in full SDLC", "twitter": "sebichondo", "pic": "https://droidcon.co.ke/img/Speakers/Stephen_Ebichondo.jpg" },
	{ "name": "Seth Kigen", "job": "Systems Architect, Twigafoods", "twitter": "kigen", "pic": "https://droidcon.co.ke/img/Speakers/Seth_Kigen.jpg" }
]